{
  "games": [
    {
      "id": "61172a252a3443cd8a69fd23564dd6c9",
      "owner": "someone.else@example.com",
      "state": 0,
      "mode": "target",
      "players": [
        {
          "email": "someone.else@example.com",
          "team": 1,
          "state": 2
        },
        {
          "email": "nobody@illinois.edu",
          "team": 0,
          "state": 0
        }
      ]
    },
    {
      "id": "2632754d6f4747ddb593f8407ebd844a",
      "owner": "nobody@illinois.edu",
      "state": 0,
      "mode": "target",
      "players": [
        {
          "email": "nobody@illinois.edu",
          "team": 1,
          "state": 2
        }
      ]
    },
    {
      "id": "9ad1bd7434d44e2499267fbe5f0cccd9",
      "owner": "yet.another@example.com",
      "state": 1,
      "mode": "area",
      "players": [
        {
          "email": "yet.another@example.com",
          "team": 1,
          "state": 3
        },
        {
          "email": "nobody@illinois.edu",
          "team": 0,
          "state": 2
        }
      ]
    },
    {
      "id": "2e51757fc21e4c08b9be67d3d3957309",
      "owner": "nobody@illinois.edu",
      "state": 2,
      "mode": "area",
      "players": [
        {
          "email": "nobody@illinois.edu",
          "team": 1,
          "state": 2
        },
        {
          "email": "invitee@example.com",
          "team": 0,
          "state": 0
        }
      ]
    },
    {
      "id": "5e653f6b43574c2ab64db13c87ae8651",
      "owner": "another@example.com",
      "state": 1,
      "mode": "area",
      "players": [
        {
          "email": "another@example.com",
          "team": 0,
          "state": 2
        },
        {
          "email": "third@example.com",
          "team": 2,
          "state": 1
        },
        {
          "email": "nobody@illinois.edu",
          "team": 3,
          "state": 0
        }
      ]
    }
  ]
}